ushuffle.so
ushuffle-1.0.dist-info/DESCRIPTION.rst
ushuffle-1.0.dist-info/METADATA
ushuffle-1.0.dist-info/RECORD
ushuffle-1.0.dist-info/WHEEL
ushuffle-1.0.dist-info/metadata.json
ushuffle-1.0.dist-info/top_level.txt
