Metadata-Version: 2.0
Name: ushuffle
Version: 1.0
Summary: A Cython wrapper over uShuffle - a useful tool for shuffling biological sequences while preserving the k-let counts.
Home-page: https://github.com/guma44/ushuffle
Author: Rafal Gumienny
Author-email: guma44@gmail.com
License: BSD license
Keywords: ushuffle
Platform: UNKNOWN
Classifier: Development Status :: 4 - Beta
Classifier: Intended Audience :: Science/Research
Classifier: License :: OSI Approved :: BSD License
Classifier: Natural Language :: English
Classifier: Programming Language :: Python :: 2
Classifier: Programming Language :: Python :: 2.6
Classifier: Programming Language :: Python :: 2.7
Classifier: Programming Language :: Python :: 3
Classifier: Programming Language :: Python :: 3.3
Classifier: Programming Language :: Python :: 3.4
Classifier: Programming Language :: Python :: 3.5
Requires-Dist: Cython (>=0.27)
